[
 {
  "title": "Î†Î³Î³ÎµÎ»Î¿Ï‚",
  "name": "Î†Î³Î³ÎµÎ»Î¿Ï‚",
  "url": "https:\/\/en.wiktionary.org\/w\/api.php",
  "category_type": "surnames",
  "status": "WikiRecordStatus.page",
  "language_id": "ell",
  "language_script": "Greek",
  "gender": "Gender.unisex",
  "parent_cmtitle": "Category:Greek surnames"
 },
 {
  "title": "Î‘Î³Î³Î­Î»Î¿Ï…",
  "name": "Î‘Î³Î³Î­Î»Î¿Ï…",
  "url": "https:\/\/en.wiktionary.org\/w\/api.php",
  "category_type": "surnames",
  "status": "WikiRecordStatus.page",
  "language_id": "ell",
  "language_script": "Greek",
  "gender": "Gender.unisex",
  "parent_cmtitle": "Category:Greek surnames"
 },
 {
  "title": "Î‘Î¸Î±Î½Î±ÏƒÎ¬ÎºÎ·",
  "name": "Î‘Î¸Î±Î½Î±ÏƒÎ¬ÎºÎ·",
  "url": "https:\/\/en.wiktionary.org\/w\/api.php",
  "category_type": "surnames",
  "status": "WikiRecordStatus.page",
  "language_id": "ell",
  "language_script": "Greek",
  "gender": "Gender.unisex",
  "parent_cmtitle": "Category:Greek surnames"
 },
 {
  "title": "Î‘Î¸Î±Î½Î±ÏƒÎ¬ÎºÎ·Ï‚",
  "name": "Î‘Î¸Î±Î½Î±ÏƒÎ¬ÎºÎ·Ï‚",
  "url": "https:\/\/en.wiktionary.org\/w\/api.php",
  "category_type": "surnames",
  "status": "WikiRecordStatus.page",
  "language_id": "ell",
  "language_script": "Greek",
  "gender": "Gender.unisex",
  "parent_cmtitle": "Category:Greek surnames"
 },
 {
  "title": "Î‘Î¸Î±Î½Î±ÏƒÎ­Î»Î·Ï‚",
  "name": "Î‘Î¸Î±Î½Î±ÏƒÎ­Î»Î·Ï‚",
  "url": "https:\/\/en.wiktionary.org\/w\/api.php",
  "category_type": "surnames",
  "status": "WikiRecordStatus.page",
  "language_id": "ell",
  "language_script": "Greek",
  "gender": "Gender.unisex",
  "parent_cmtitle": "Category:Greek surnames"
 },
 {
  "title": "Î‘Î¸Î±Î½Î±ÏƒÎ­Î»Î»Î·Ï‚",
  "name": "Î‘Î¸Î±Î½Î±ÏƒÎ­Î»Î»Î·Ï‚",
  "url": "https:\/\/en.wiktionary.org\/w\/api.php",
  "category_type": "surnames",
  "status": "WikiRecordStatus.page",
  "language_id": "ell",
  "language_script": "Greek",
  "gender": "Gender.unisex",
  "parent_cmtitle": "Category:Greek surnames"
 },
 {
  "title": "Î‘Î½Ï„Ï‰Î½Î¬ÎºÎ·",
  "name": "Î‘Î½Ï„Ï‰Î½Î¬ÎºÎ·",
  "url": "https:\/\/en.wiktionary.org\/w\/api.php",
  "category_type": "surnames",
  "status": "WikiRecordStatus.page",
  "language_id": "ell",
  "language_script": "Greek",
  "gender": "Gender.unisex",
  "parent_cmtitle": "Category:Greek surnames"
 },
 {
  "title": "Î‘Î½Ï„Ï‰Î½Î¬ÎºÎ·Ï‚",
  "name": "Î‘Î½Ï„Ï‰Î½Î¬ÎºÎ·Ï‚",
  "url": "https:\/\/en.wiktionary.org\/w\/api.php",
  "category_type": "surnames",
  "status": "WikiRecordStatus.page",
  "language_id": "ell",
  "language_script": "Greek",
  "gender": "Gender.unisex",
  "parent_cmtitle": "Category:Greek surnames"
 },
 {
  "title": "Î‘ÏÎ²Î±Î½Î¹Ï„ÏŒÏ€Î¿Ï…Î»Î»Î¿Ï‚",
  "name": "Î‘ÏÎ²Î±Î½Î¹Ï„ÏŒÏ€Î¿Ï…Î»Î»Î¿Ï‚",
  "url": "https:\/\/en.wiktionary.org\/w\/api.php",
  "category_type": "surnames",
  "status": "WikiRecordStatus.page",
  "language_id": "ell",
  "language_script": "Greek",
  "gender": "Gender.unisex",
  "parent_cmtitle": "Category:Greek surnames"
 },
 {
  "title": "Î‘ÏÎ²Î±Î½Î¹Ï„ÏŒÏ€Î¿Ï…Î»Î¿Ï‚",
  "name": "Î‘ÏÎ²Î±Î½Î¹Ï„ÏŒÏ€Î¿Ï…Î»Î¿Ï‚",
  "url": "https:\/\/en.wiktionary.org\/w\/api.php",
  "category_type": "surnames",
  "status": "WikiRecordStatus.page",
  "language_id": "ell",
  "language_script": "Greek",
  "gender": "Gender.unisex",
  "parent_cmtitle": "Category:Greek surnames"
 },
 {
  "title": "Î“Î¹Î±Î½Î½Î¬ÎºÎ·",
  "name": "Î“Î¹Î±Î½Î½Î¬ÎºÎ·",
  "url": "https:\/\/en.wiktionary.org\/w\/api.php",
  "category_type": "surnames",
  "status": "WikiRecordStatus.page",
  "language_id": "ell",
  "language_script": "Greek",
  "gender": "Gender.unisex",
  "parent_cmtitle": "Category:Greek surnames"
 },
 {
  "title": "Î“Î¹Î±Î½Î½Î¬ÎºÎ·Ï‚",
  "name": "Î“Î¹Î±Î½Î½Î¬ÎºÎ·Ï‚",
  "url": "https:\/\/en.wiktionary.org\/w\/api.php",
  "category_type": "surnames",
  "status": "WikiRecordStatus.page",
  "language_id": "ell",
  "language_script": "Greek",
  "gender": "Gender.unisex",
  "parent_cmtitle": "Category:Greek surnames"
 },
 {
  "title": "Î”Î·Î¼Î·Ï„ÏÎ¬ÎºÎ·",
  "name": "Î”Î·Î¼Î·Ï„ÏÎ¬ÎºÎ·",
  "url": "https:\/\/en.wiktionary.org\/w\/api.php",
  "category_type": "surnames",
  "status": "WikiRecordStatus.page",
  "language_id": "ell",
  "language_script": "Greek",
  "gender": "Gender.unisex",
  "parent_cmtitle": "Category:Greek surnames"
 },
 {
  "title": "Î”Î·Î¼Î·Ï„ÏÎ¬ÎºÎ·Ï‚",
  "name": "Î”Î·Î¼Î·Ï„ÏÎ¬ÎºÎ·Ï‚",
  "url": "https:\/\/en.wiktionary.org\/w\/api.php",
  "category_type": "surnames",
  "status": "WikiRecordStatus.page",
  "language_id": "ell",
  "language_script": "Greek",
  "gender": "Gender.unisex",
  "parent_cmtitle": "Category:Greek surnames"
 },
 {
  "title": "Î”ÏÎ±ÎºÏŒÏ€Î¿Ï…Î»Î¿Ï‚",
  "name": "Î”ÏÎ±ÎºÏŒÏ€Î¿Ï…Î»Î¿Ï‚",
  "url": "https:\/\/en.wiktionary.org\/w\/api.php",
  "category_type": "surnames",
  "status": "WikiRecordStatus.page",
  "language_id": "ell",
  "language_script": "Greek",
  "gender": "Gender.unisex",
  "parent_cmtitle": "Category:Greek surnames"
 },
 {
  "title": "Î•Î»ÎµÏ…Î¸ÎµÏÎ¿Ï…Î´Î¬ÎºÎ·",
  "name": "Î•Î»ÎµÏ…Î¸ÎµÏÎ¿Ï…Î´Î¬ÎºÎ·",
  "url": "https:\/\/en.wiktionary.org\/w\/api.php",
  "category_type": "surnames",
  "status": "WikiRecordStatus.page",
  "language_id": "ell",
  "language_script": "Greek",
  "gender": "Gender.unisex",
  "parent_cmtitle": "Category:Greek surnames"
 },
 {
  "title": "Î•Î»ÎµÏ…Î¸ÎµÏÎ¿Ï…Î´Î¬ÎºÎ·Ï‚",
  "name": "Î•Î»ÎµÏ…Î¸ÎµÏÎ¿Ï…Î´Î¬ÎºÎ·Ï‚",
  "url": "https:\/\/en.wiktionary.org\/w\/api.php",
  "category_type": "surnames",
  "status": "WikiRecordStatus.page",
  "language_id": "ell",
  "language_script": "Greek",
  "gender": "Gender.unisex",
  "parent_cmtitle": "Category:Greek surnames"
 },
 {
  "title": "Î˜ÎµÎ¿Î´Ï‰ÏÎ¬ÎºÎ·Ï‚",
  "name": "Î˜ÎµÎ¿Î´Ï‰ÏÎ¬ÎºÎ·Ï‚",
  "url": "https:\/\/en.wiktionary.org\/w\/api.php",
  "category_type": "surnames",
  "status": "WikiRecordStatus.page",
  "language_id": "ell",
  "language_script": "Greek",
  "gender": "Gender.unisex",
  "parent_cmtitle": "Category:Greek surnames"
 },
 {
  "title": "Î˜ÎµÎ¿Î´Ï‰ÏÎ¯Î´Î·Ï‚",
  "name": "Î˜ÎµÎ¿Î´Ï‰ÏÎ¯Î´Î·Ï‚",
  "url": "https:\/\/en.wiktionary.org\/w\/api.php",
  "category_type": "surnames",
  "status": "WikiRecordStatus.page",
  "language_id": "ell",
  "language_script": "Greek",
  "gender": "Gender.unisex",
  "parent_cmtitle": "Category:Greek surnames"
 },
 {
  "title": "Î™Ï‰Î¬Î½Î½Î¿Ï…",
  "name": "Î™Ï‰Î¬Î½Î½Î¿Ï…",
  "url": "https:\/\/en.wiktionary.org\/w\/api.php",
  "category_type": "surnames",
  "status": "WikiRecordStatus.page",
  "language_id": "ell",
  "language_script": "Greek",
  "gender": "Gender.unisex",
  "parent_cmtitle": "Category:Greek surnames"
 },
 {
  "title": "ÎšÎ±Î¶Î¬ÎºÎ¿Ï‚",
  "name": "ÎšÎ±Î¶Î¬ÎºÎ¿Ï‚",
  "url": "https:\/\/en.wiktionary.org\/w\/api.php",
  "category_type": "surnames",
  "status": "WikiRecordStatus.page",
  "language_id": "ell",
  "language_script": "Greek",
  "gender": "Gender.unisex",
  "parent_cmtitle": "Category:Greek surnames"
 },
 {
  "title": "ÎšÎ±ÏÎ³Î±Î´Î¿ÏÏÎ·Ï‚",
  "name": "ÎšÎ±ÏÎ³Î±Î´Î¿ÏÏÎ·Ï‚",
  "url": "https:\/\/en.wiktionary.org\/w\/api.php",
  "category_type": "surnames",
  "status": "WikiRecordStatus.page",
  "language_id": "ell",
  "language_script": "Greek",
  "gender": "Gender.unisex",
  "parent_cmtitle": "Category:Greek surnames"
 },
 {
  "title": "ÎšÏ‰ÏƒÏ„Î¬ÎºÎ·Ï‚",
  "name": "ÎšÏ‰ÏƒÏ„Î¬ÎºÎ·Ï‚",
  "url": "https:\/\/en.wiktionary.org\/w\/api.php",
  "category_type": "surnames",
  "status": "WikiRecordStatus.page",
  "language_id": "ell",
  "language_script": "Greek",
  "gender": "Gender.unisex",
  "parent_cmtitle": "Category:Greek surnames"
 },
 {
  "title": "ÎœÎ±Ï„Î¸Î±Î¯Î¿Ï…",
  "name": "ÎœÎ±Ï„Î¸Î±Î¯Î¿Ï…",
  "url": "https:\/\/en.wiktionary.org\/w\/api.php",
  "category_type": "surnames",
  "status": "WikiRecordStatus.page",
  "language_id": "ell",
  "language_script": "Greek",
  "gender": "Gender.unisex",
  "parent_cmtitle": "Category:Greek surnames"
 },
 {
  "title": "ÎœÎ¹ÎºÏÎ¿ÏÏ„ÏƒÎ¹ÎºÎ¿Ï‚",
  "name": "ÎœÎ¹ÎºÏÎ¿ÏÏ„ÏƒÎ¹ÎºÎ¿Ï‚",
  "url": "https:\/\/en.wiktionary.org\/w\/api.php",
  "category_type": "surnames",
  "status": "WikiRecordStatus.page",
  "language_id": "ell",
  "language_script": "Greek",
  "gender": "Gender.unisex",
  "parent_cmtitle": "Category:Greek surnames"
 },
 {
  "title": "ÎœÏ€Î¬ÏÎ¿Ï‚",
  "name": "ÎœÏ€Î¬ÏÎ¿Ï‚",
  "url": "https:\/\/en.wiktionary.org\/w\/api.php",
  "category_type": "surnames",
  "status": "WikiRecordStatus.page",
  "language_id": "ell",
  "language_script": "Greek",
  "gender": "Gender.unisex",
  "parent_cmtitle": "Category:Greek surnames"
 },
 {
  "title": "ÎÎ¹ÎºÎ¿Î»Î¬Î¿Ï…",
  "name": "ÎÎ¹ÎºÎ¿Î»Î¬Î¿Ï…",
  "url": "https:\/\/en.wiktionary.org\/w\/api.php",
  "category_type": "surnames",
  "status": "WikiRecordStatus.page",
  "language_id": "ell",
  "language_script": "Greek",
  "gender": "Gender.unisex",
  "parent_cmtitle": "Category:Greek surnames"
 },
 {
  "title": "ÎŸÏÎ»Î¬Î½Î´Î¿Ï‚",
  "name": "ÎŸÏÎ»Î¬Î½Î´Î¿Ï‚",
  "url": "https:\/\/en.wiktionary.org\/w\/api.php",
  "category_type": "surnames",
  "status": "WikiRecordStatus.page",
  "language_id": "ell",
  "language_script": "Greek",
  "gender": "Gender.unisex",
  "parent_cmtitle": "Category:Greek surnames"
 },
 {
  "title": "Î Î±ÏÎ±ÏƒÎºÎµÏ…ÏŒÏ€Î¿Ï…Î»Î¿Ï‚",
  "name": "Î Î±ÏÎ±ÏƒÎºÎµÏ…ÏŒÏ€Î¿Ï…Î»Î¿Ï‚",
  "url": "https:\/\/en.wiktionary.org\/w\/api.php",
  "category_type": "surnames",
  "status": "WikiRecordStatus.page",
  "language_id": "ell",
  "language_script": "Greek",
  "gender": "Gender.unisex",
  "parent_cmtitle": "Category:Greek surnames"
 },
 {
  "title": "Î Î±ÏÎ±ÏƒÎºÎµÏ…Î¿Ï€Î¿ÏÎ»Î¿Ï…",
  "name": "Î Î±ÏÎ±ÏƒÎºÎµÏ…Î¿Ï€Î¿ÏÎ»Î¿Ï…",
  "url": "https:\/\/en.wiktionary.org\/w\/api.php",
  "category_type": "surnames",
  "status": "WikiRecordStatus.page",
  "language_id": "ell",
  "language_script": "Greek",
  "gender": "Gender.unisex",
  "parent_cmtitle": "Category:Greek surnames"
 },
 {
  "title": "Î Î±Ï…Î»Î¬ÎºÎ·",
  "name": "Î Î±Ï…Î»Î¬ÎºÎ·",
  "url": "https:\/\/en.wiktionary.org\/w\/api.php",
  "category_type": "surnames",
  "status": "WikiRecordStatus.page",
  "language_id": "ell",
  "language_script": "Greek",
  "gender": "Gender.unisex",
  "parent_cmtitle": "Category:Greek surnames"
 },
 {
  "title": "Î Î±Ï…Î»Î¬ÎºÎ·Ï‚",
  "name": "Î Î±Ï…Î»Î¬ÎºÎ·Ï‚",
  "url": "https:\/\/en.wiktionary.org\/w\/api.php",
  "category_type": "surnames",
  "status": "WikiRecordStatus.page",
  "language_id": "ell",
  "language_script": "Greek",
  "gender": "Gender.unisex",
  "parent_cmtitle": "Category:Greek surnames"
 },
 {
  "title": "Î ÎµÏ„ÏÎ¬ÎºÎ·",
  "name": "Î ÎµÏ„ÏÎ¬ÎºÎ·",
  "url": "https:\/\/en.wiktionary.org\/w\/api.php",
  "category_type": "surnames",
  "status": "WikiRecordStatus.page",
  "language_id": "ell",
  "language_script": "Greek",
  "gender": "Gender.unisex",
  "parent_cmtitle": "Category:Greek surnames"
 },
 {
  "title": "Î ÎµÏ„ÏÎ¬ÎºÎ·Ï‚",
  "name": "Î ÎµÏ„ÏÎ¬ÎºÎ·Ï‚",
  "url": "https:\/\/en.wiktionary.org\/w\/api.php",
  "category_type": "surnames",
  "status": "WikiRecordStatus.page",
  "language_id": "ell",
  "language_script": "Greek",
  "gender": "Gender.unisex",
  "parent_cmtitle": "Category:Greek surnames"
 },
 {
  "title": "Î¤Î¶Î­Ï„Î¶Î·Ï‚",
  "name": "Î¤Î¶Î­Ï„Î¶Î·Ï‚",
  "url": "https:\/\/en.wiktionary.org\/w\/api.php",
  "category_type": "surnames",
  "status": "WikiRecordStatus.page",
  "language_id": "ell",
  "language_script": "Greek",
  "gender": "Gender.unisex",
  "parent_cmtitle": "Category:Greek surnames"
 },
 {
  "title": "Î¤ÏƒÎ¿Î»Î¬ÎºÎ·Ï‚",
  "name": "Î¤ÏƒÎ¿Î»Î¬ÎºÎ·Ï‚",
  "url": "https:\/\/en.wiktionary.org\/w\/api.php",
  "category_type": "surnames",
  "status": "WikiRecordStatus.page",
  "language_id": "ell",
  "language_script": "Greek",
  "gender": "Gender.unisex",
  "parent_cmtitle": "Category:Greek surnames"
 },
 {
  "title": "Î¦Î±ÎºÎ¯ÏÎ·",
  "name": "Î¦Î±ÎºÎ¯ÏÎ·",
  "url": "https:\/\/en.wiktionary.org\/w\/api.php",
  "category_type": "surnames",
  "status": "WikiRecordStatus.page",
  "language_id": "ell",
  "language_script": "Greek",
  "gender": "Gender.unisex",
  "parent_cmtitle": "Category:Greek surnames"
 },
 {
  "title": "Î¦Î±ÎºÎ¯ÏÎ·Ï‚",
  "name": "Î¦Î±ÎºÎ¯ÏÎ·Ï‚",
  "url": "https:\/\/en.wiktionary.org\/w\/api.php",
  "category_type": "surnames",
  "status": "WikiRecordStatus.page",
  "language_id": "ell",
  "language_script": "Greek",
  "gender": "Gender.unisex",
  "parent_cmtitle": "Category:Greek surnames"
 },
 {
  "title": "Î§ÏÎ·ÏƒÏ„Î¬ÎºÎ·Ï‚",
  "name": "Î§ÏÎ·ÏƒÏ„Î¬ÎºÎ·Ï‚",
  "url": "https:\/\/en.wiktionary.org\/w\/api.php",
  "category_type": "surnames",
  "status": "WikiRecordStatus.page",
  "language_id": "ell",
  "language_script": "Greek",
  "gender": "Gender.unisex",
  "parent_cmtitle": "Category:Greek surnames"
 },
 {
  "title": "Î§ÏÎ·ÏƒÏ„Î¬ÎºÎ¿Ï‚",
  "name": "Î§ÏÎ·ÏƒÏ„Î¬ÎºÎ¿Ï‚",
  "url": "https:\/\/en.wiktionary.org\/w\/api.php",
  "category_type": "surnames",
  "status": "WikiRecordStatus.page",
  "language_id": "ell",
  "language_script": "Greek",
  "gender": "Gender.unisex",
  "parent_cmtitle": "Category:Greek surnames"
 },
 {
  "title": "Î§ÏÎ¹ÏƒÏ„Î¬ÎºÎ·Ï‚",
  "name": "Î§ÏÎ¹ÏƒÏ„Î¬ÎºÎ·Ï‚",
  "url": "https:\/\/en.wiktionary.org\/w\/api.php",
  "category_type": "surnames",
  "status": "WikiRecordStatus.page",
  "language_id": "ell",
  "language_script": "Greek",
  "gender": "Gender.unisex",
  "parent_cmtitle": "Category:Greek surnames"
 },
 {
  "title": "Î§ÏÎ¹ÏƒÏ„Î¬ÎºÎ¿Ï‚",
  "name": "Î§ÏÎ¹ÏƒÏ„Î¬ÎºÎ¿Ï‚",
  "url": "https:\/\/en.wiktionary.org\/w\/api.php",
  "category_type": "surnames",
  "status": "WikiRecordStatus.page",
  "language_id": "ell",
  "language_script": "Greek",
  "gender": "Gender.unisex",
  "parent_cmtitle": "Category:Greek surnames"
 },
 {
  "title": "Î¨Î¬ÎºÎ·Ï‚",
  "name": "Î¨Î¬ÎºÎ·Ï‚",
  "url": "https:\/\/en.wiktionary.org\/w\/api.php",
  "category_type": "surnames",
  "status": "WikiRecordStatus.page",
  "language_id": "ell",
  "language_script": "Greek",
  "gender": "Gender.unisex",
  "parent_cmtitle": "Category:Greek surnames"
 },
 {
  "title": "Adamantidis",
  "name": "Adamantidis",
  "url": "https:\/\/en.wiktionary.org\/w\/api.php",
  "category_type": "surnames",
  "status": "WikiRecordStatus.page",
  "language_id": "ell",
  "language_script": "Latin",
  "gender": "Gender.unisex",
  "parent_cmtitle": "Category:English surnames from Greek"
 },
 {
  "title": "Alexopoulos",
  "name": "Alexopoulos",
  "url": "https:\/\/en.wiktionary.org\/w\/api.php",
  "category_type": "surnames",
  "status": "WikiRecordStatus.page",
  "language_id": "ell",
  "language_script": "Latin",
  "gender": "Gender.unisex",
  "parent_cmtitle": "Category:English surnames from Greek"
 },
 {
  "title": "Anastos",
  "name": "Anastos",
  "url": "https:\/\/en.wiktionary.org\/w\/api.php",
  "category_type": "surnames",
  "status": "WikiRecordStatus.page",
  "language_id": "ell",
  "language_script": "Latin",
  "gender": "Gender.unisex",
  "parent_cmtitle": "Category:English surnames from Greek"
 },
 {
  "title": "Antoniou",
  "name": "Antoniou",
  "url": "https:\/\/en.wiktionary.org\/w\/api.php",
  "category_type": "surnames",
  "status": "WikiRecordStatus.page",
  "language_id": "ell",
  "language_script": "Latin",
  "gender": "Gender.unisex",
  "parent_cmtitle": "Category:English surnames from Greek"
 },
 {
  "title": "Antonopoulos",
  "name": "Antonopoulos",
  "url": "https:\/\/en.wiktionary.org\/w\/api.php",
  "category_type": "surnames",
  "status": "WikiRecordStatus.page",
  "language_id": "ell",
  "language_script": "Latin",
  "gender": "Gender.unisex",
  "parent_cmtitle": "Category:English surnames from Greek"
 },
 {
  "title": "Antzoulides",
  "name": "Antzoulides",
  "url": "https:\/\/en.wiktionary.org\/w\/api.php",
  "category_type": "surnames",
  "status": "WikiRecordStatus.page",
  "language_id": "ell",
  "language_script": "Latin",
  "gender": "Gender.unisex",
  "parent_cmtitle": "Category:English surnames from Greek"
 },
 {
  "title": "Arvanitis",
  "name": "Arvanitis",
  "url": "https:\/\/en.wiktionary.org\/w\/api.php",
  "category_type": "surnames",
  "status": "WikiRecordStatus.page",
  "language_id": "ell",
  "language_script": "Latin",
  "gender": "Gender.unisex",
  "parent_cmtitle": "Category:English surnames from Greek"
 },
 {
  "title": "Athanaselis",
  "name": "Athanaselis",
  "url": "https:\/\/en.wiktionary.org\/w\/api.php",
  "category_type": "surnames",
  "status": "WikiRecordStatus.page",
  "language_id": "ell",
  "language_script": "Latin",
  "gender": "Gender.unisex",
  "parent_cmtitle": "Category:English surnames from Greek"
 },
 {
  "title": "Athanasellis",
  "name": "Athanasellis",
  "url": "https:\/\/en.wiktionary.org\/w\/api.php",
  "category_type": "surnames",
  "status": "WikiRecordStatus.page",
  "language_id": "ell",
  "language_script": "Latin",
  "gender": "Gender.unisex",
  "parent_cmtitle": "Category:English surnames from Greek"
 },
 {
  "title": "Athens",
  "name": "Athens",
  "url": "https:\/\/en.wiktionary.org\/w\/api.php",
  "category_type": "surnames",
  "status": "WikiRecordStatus.page",
  "language_id": "ell",
  "language_script": "Latin",
  "gender": "Gender.unisex",
  "parent_cmtitle": "Category:English surnames from Greek"
 },
 {
  "title": "Bakas",
  "name": "Bakas",
  "url": "https:\/\/en.wiktionary.org\/w\/api.php",
  "category_type": "surnames",
  "status": "WikiRecordStatus.page",
  "language_id": "ell",
  "language_script": "Latin",
  "gender": "Gender.unisex",
  "parent_cmtitle": "Category:English surnames from Greek"
 },
 {
  "title": "Christodoulou",
  "name": "Christodoulou",
  "url": "https:\/\/en.wiktionary.org\/w\/api.php",
  "category_type": "surnames",
  "status": "WikiRecordStatus.page",
  "language_id": "ell",
  "language_script": "Latin",
  "gender": "Gender.unisex",
  "parent_cmtitle": "Category:English surnames from Greek"
 },
 {
  "title": "Christopoulos",
  "name": "Christopoulos",
  "url": "https:\/\/en.wiktionary.org\/w\/api.php",
  "category_type": "surnames",
  "status": "WikiRecordStatus.page",
  "language_id": "ell",
  "language_script": "Latin",
  "gender": "Gender.unisex",
  "parent_cmtitle": "Category:English surnames from Greek"
 },
 {
  "title": "Condos",
  "name": "Condos",
  "url": "https:\/\/en.wiktionary.org\/w\/api.php",
  "category_type": "surnames",
  "status": "WikiRecordStatus.page",
  "language_id": "ell",
  "language_script": "Latin",
  "gender": "Gender.unisex",
  "parent_cmtitle": "Category:English surnames from Greek"
 },
 {
  "title": "Contos",
  "name": "Contos",
  "url": "https:\/\/en.wiktionary.org\/w\/api.php",
  "category_type": "surnames",
  "status": "WikiRecordStatus.page",
  "language_id": "ell",
  "language_script": "Latin",
  "gender": "Gender.unisex",
  "parent_cmtitle": "Category:English surnames from Greek"
 },
 {
  "title": "Demetriou",
  "name": "Demetriou",
  "url": "https:\/\/en.wiktionary.org\/w\/api.php",
  "category_type": "surnames",
  "status": "WikiRecordStatus.page",
  "language_id": "ell",
  "language_script": "Latin",
  "gender": "Gender.unisex",
  "parent_cmtitle": "Category:English surnames from Greek"
 },
 {
  "title": "Donis",
  "name": "Donis",
  "url": "https:\/\/en.wiktionary.org\/w\/api.php",
  "category_type": "surnames",
  "status": "WikiRecordStatus.page",
  "language_id": "ell",
  "language_script": "Latin",
  "gender": "Gender.unisex",
  "parent_cmtitle": "Category:English surnames from Greek"
 },
 {
  "title": "Doukas",
  "name": "Doukas",
  "url": "https:\/\/en.wiktionary.org\/w\/api.php",
  "category_type": "surnames",
  "status": "WikiRecordStatus.page",
  "language_id": "ell",
  "language_script": "Latin",
  "gender": "Gender.unisex",
  "parent_cmtitle": "Category:English surnames from Greek"
 },
 {
  "title": "Economos",
  "name": "Economos",
  "url": "https:\/\/en.wiktionary.org\/w\/api.php",
  "category_type": "surnames",
  "status": "WikiRecordStatus.page",
  "language_id": "ell",
  "language_script": "Latin",
  "gender": "Gender.unisex",
  "parent_cmtitle": "Category:English surnames from Greek"
 },
 {
  "title": "Eliopoulos",
  "name": "Eliopoulos",
  "url": "https:\/\/en.wiktionary.org\/w\/api.php",
  "category_type": "surnames",
  "status": "WikiRecordStatus.page",
  "language_id": "ell",
  "language_script": "Latin",
  "gender": "Gender.unisex",
  "parent_cmtitle": "Category:English surnames from Greek"
 },
 {
  "title": "Fotopoulos",
  "name": "Fotopoulos",
  "url": "https:\/\/en.wiktionary.org\/w\/api.php",
  "category_type": "surnames",
  "status": "WikiRecordStatus.page",
  "language_id": "ell",
  "language_script": "Latin",
  "gender": "Gender.unisex",
  "parent_cmtitle": "Category:English surnames from Greek"
 },
 {
  "title": "Galanis",
  "name": "Galanis",
  "url": "https:\/\/en.wiktionary.org\/w\/api.php",
  "category_type": "surnames",
  "status": "WikiRecordStatus.page",
  "language_id": "ell",
  "language_script": "Latin",
  "gender": "Gender.unisex",
  "parent_cmtitle": "Category:English surnames from Greek"
 },
 {
  "title": "Georgiadis",
  "name": "Georgiadis",
  "url": "https:\/\/en.wiktionary.org\/w\/api.php",
  "category_type": "surnames",
  "status": "WikiRecordStatus.page",
  "language_id": "ell",
  "language_script": "Latin",
  "gender": "Gender.unisex",
  "parent_cmtitle": "Category:English surnames from Greek"
 },
 {
  "title": "Georgopoulos",
  "name": "Georgopoulos",
  "url": "https:\/\/en.wiktionary.org\/w\/api.php",
  "category_type": "surnames",
  "status": "WikiRecordStatus.page",
  "language_id": "ell",
  "language_script": "Latin",
  "gender": "Gender.unisex",
  "parent_cmtitle": "Category:English surnames from Greek"
 },
 {
  "title": "Gerakitis",
  "name": "Gerakitis",
  "url": "https:\/\/en.wiktionary.org\/w\/api.php",
  "category_type": "surnames",
  "status": "WikiRecordStatus.page",
  "language_id": "ell",
  "language_script": "Latin",
  "gender": "Gender.unisex",
  "parent_cmtitle": "Category:English surnames from Greek"
 },
 {
  "title": "Glynos",
  "name": "Glynos",
  "url": "https:\/\/en.wiktionary.org\/w\/api.php",
  "category_type": "surnames",
  "status": "WikiRecordStatus.page",
  "language_id": "ell",
  "language_script": "Latin",
  "gender": "Gender.unisex",
  "parent_cmtitle": "Category:English surnames from Greek"
 },
 {
  "title": "Iliopoulos",
  "name": "Iliopoulos",
  "url": "https:\/\/en.wiktionary.org\/w\/api.php",
  "category_type": "surnames",
  "status": "WikiRecordStatus.page",
  "language_id": "ell",
  "language_script": "Latin",
  "gender": "Gender.unisex",
  "parent_cmtitle": "Category:English surnames from Greek"
 },
 {
  "title": "Ioannidis",
  "name": "Ioannidis",
  "url": "https:\/\/en.wiktionary.org\/w\/api.php",
  "category_type": "surnames",
  "status": "WikiRecordStatus.page",
  "language_id": "ell",
  "language_script": "Latin",
  "gender": "Gender.unisex",
  "parent_cmtitle": "Category:English surnames from Greek"
 },
 {
  "title": "Katsaros",
  "name": "Katsaros",
  "url": "https:\/\/en.wiktionary.org\/w\/api.php",
  "category_type": "surnames",
  "status": "WikiRecordStatus.page",
  "language_id": "ell",
  "language_script": "Latin",
  "gender": "Gender.unisex",
  "parent_cmtitle": "Category:English surnames from Greek"
 },
 {
  "title": "Kazan",
  "name": "Kazan",
  "url": "https:\/\/en.wiktionary.org\/w\/api.php",
  "category_type": "surnames",
  "status": "WikiRecordStatus.page",
  "language_id": "ell",
  "language_script": "Latin",
  "gender": "Gender.unisex",
  "parent_cmtitle": "Category:English surnames from Greek"
 },
 {
  "title": "Kellis",
  "name": "Kellis",
  "url": "https:\/\/en.wiktionary.org\/w\/api.php",
  "category_type": "surnames",
  "status": "WikiRecordStatus.page",
  "language_id": "ell",
  "language_script": "Latin",
  "gender": "Gender.unisex",
  "parent_cmtitle": "Category:English surnames from Greek"
 },
 {
  "title": "Kosta",
  "name": "Kosta",
  "url": "https:\/\/en.wiktionary.org\/w\/api.php",
  "category_type": "surnames",
  "status": "WikiRecordStatus.page",
  "language_id": "ell",
  "language_script": "Latin",
  "gender": "Gender.unisex",
  "parent_cmtitle": "Category:English surnames from Greek"
 },
 {
  "title": "Koudanis",
  "name": "Koudanis",
  "url": "https:\/\/en.wiktionary.org\/w\/api.php",
  "category_type": "surnames",
  "status": "WikiRecordStatus.page",
  "language_id": "ell",
  "language_script": "Latin",
  "gender": "Gender.unisex",
  "parent_cmtitle": "Category:English surnames from Greek"
 },
 {
  "title": "Lambros",
  "name": "Lambros",
  "url": "https:\/\/en.wiktionary.org\/w\/api.php",
  "category_type": "surnames",
  "status": "WikiRecordStatus.page",
  "language_id": "ell",
  "language_script": "Latin",
  "gender": "Gender.unisex",
  "parent_cmtitle": "Category:English surnames from Greek"
 },
 {
  "title": "Lekas",
  "name": "Lekas",
  "url": "https:\/\/en.wiktionary.org\/w\/api.php",
  "category_type": "surnames",
  "status": "WikiRecordStatus.page",
  "language_id": "ell",
  "language_script": "Latin",
  "gender": "Gender.unisex",
  "parent_cmtitle": "Category:English surnames from Greek"
 },
 {
  "title": "Livas",
  "name": "Livas",
  "url": "https:\/\/en.wiktionary.org\/w\/api.php",
  "category_type": "surnames",
  "status": "WikiRecordStatus.page",
  "language_id": "ell",
  "language_script": "Latin",
  "gender": "Gender.unisex",
  "parent_cmtitle": "Category:English surnames from Greek"
 },
 {
  "title": "Makris",
  "name": "Makris",
  "url": "https:\/\/en.wiktionary.org\/w\/api.php",
  "category_type": "surnames",
  "status": "WikiRecordStatus.page",
  "language_id": "ell",
  "language_script": "Latin",
  "gender": "Gender.unisex",
  "parent_cmtitle": "Category:English surnames from Greek"
 },
 {
  "title": "Mardas",
  "name": "Mardas",
  "url": "https:\/\/en.wiktionary.org\/w\/api.php",
  "category_type": "surnames",
  "status": "WikiRecordStatus.page",
  "language_id": "ell",
  "language_script": "Latin",
  "gender": "Gender.unisex",
  "parent_cmtitle": "Category:English surnames from Greek"
 },
 {
  "title": "Mavridis",
  "name": "Mavridis",
  "url": "https:\/\/en.wiktionary.org\/w\/api.php",
  "category_type": "surnames",
  "status": "WikiRecordStatus.page",
  "language_id": "ell",
  "language_script": "Latin",
  "gender": "Gender.unisex",
  "parent_cmtitle": "Category:English surnames from Greek"
 },
 {
  "title": "Milaras",
  "name": "Milaras",
  "url": "https:\/\/en.wiktionary.org\/w\/api.php",
  "category_type": "surnames",
  "status": "WikiRecordStatus.page",
  "language_id": "ell",
  "language_script": "Latin",
  "gender": "Gender.unisex",
  "parent_cmtitle": "Category:English surnames from Greek"
 },
 {
  "title": "Milas",
  "name": "Milas",
  "url": "https:\/\/en.wiktionary.org\/w\/api.php",
  "category_type": "surnames",
  "status": "WikiRecordStatus.page",
  "language_id": "ell",
  "language_script": "Latin",
  "gender": "Gender.unisex",
  "parent_cmtitle": "Category:English surnames from Greek"
 },
 {
  "title": "Minas",
  "name": "Minas",
  "url": "https:\/\/en.wiktionary.org\/w\/api.php",
  "category_type": "surnames",
  "status": "WikiRecordStatus.page",
  "language_id": "ell",
  "language_script": "Latin",
  "gender": "Gender.unisex",
  "parent_cmtitle": "Category:English surnames from Greek"
 },
 {
  "title": "Modis",
  "name": "Modis",
  "url": "https:\/\/en.wiktionary.org\/w\/api.php",
  "category_type": "surnames",
  "status": "WikiRecordStatus.page",
  "language_id": "ell",
  "language_script": "Latin",
  "gender": "Gender.unisex",
  "parent_cmtitle": "Category:English surnames from Greek"
 },
 {
  "title": "Mourelatos",
  "name": "Mourelatos",
  "url": "https:\/\/en.wiktionary.org\/w\/api.php",
  "category_type": "surnames",
  "status": "WikiRecordStatus.page",
  "language_id": "ell",
  "language_script": "Latin",
  "gender": "Gender.unisex",
  "parent_cmtitle": "Category:English surnames from Greek"
 },
 {
  "title": "Nanos",
  "name": "Nanos",
  "url": "https:\/\/en.wiktionary.org\/w\/api.php",
  "category_type": "surnames",
  "status": "WikiRecordStatus.page",
  "language_id": "ell",
  "language_script": "Latin",
  "gender": "Gender.unisex",
  "parent_cmtitle": "Category:English surnames from Greek"
 },
 {
  "title": "Panagopoulos",
  "name": "Panagopoulos",
  "url": "https:\/\/en.wiktionary.org\/w\/api.php",
  "category_type": "surnames",
  "status": "WikiRecordStatus.page",
  "language_id": "ell",
  "language_script": "Latin",
  "gender": "Gender.unisex",
  "parent_cmtitle": "Category:English surnames from Greek"
 },
 {
  "title": "Panas",
  "name": "Panas",
  "url": "https:\/\/en.wiktionary.org\/w\/api.php",
  "category_type": "surnames",
  "status": "WikiRecordStatus.page",
  "language_id": "ell",
  "language_script": "Latin",
  "gender": "Gender.unisex",
  "parent_cmtitle": "Category:English surnames from Greek"
 },
 {
  "title": "Papadakis",
  "name": "Papadakis",
  "url": "https:\/\/en.wiktionary.org\/w\/api.php",
  "category_type": "surnames",
  "status": "WikiRecordStatus.page",
  "language_id": "ell",
  "language_script": "Latin",
  "gender": "Gender.unisex",
  "parent_cmtitle": "Category:English surnames from Greek"
 },
 {
  "title": "Papadopoulos",
  "name": "Papadopoulos",
  "url": "https:\/\/en.wiktionary.org\/w\/api.php",
  "category_type": "surnames",
  "status": "WikiRecordStatus.page",
  "language_id": "ell",
  "language_script": "Latin",
  "gender": "Gender.unisex",
  "parent_cmtitle": "Category:English surnames from Greek"
 },
 {
  "title": "Papageorge",
  "name": "Papageorge",
  "url": "https:\/\/en.wiktionary.org\/w\/api.php",
  "category_type": "surnames",
  "status": "WikiRecordStatus.page",
  "language_id": "ell",
  "language_script": "Latin",
  "gender": "Gender.unisex",
  "parent_cmtitle": "Category:English surnames from Greek"
 },
 {
  "title": "Pappas",
  "name": "Pappas",
  "url": "https:\/\/en.wiktionary.org\/w\/api.php",
  "category_type": "surnames",
  "status": "WikiRecordStatus.page",
  "language_id": "ell",
  "language_script": "Latin",
  "gender": "Gender.unisex",
  "parent_cmtitle": "Category:English surnames from Greek"
 },
 {
  "title": "Petrakis",
  "name": "Petrakis",
  "url": "https:\/\/en.wiktionary.org\/w\/api.php",
  "category_type": "surnames",
  "status": "WikiRecordStatus.page",
  "language_id": "ell",
  "language_script": "Latin",
  "gender": "Gender.unisex",
  "parent_cmtitle": "Category:English surnames from Greek"
 },
 {
  "title": "Psaki",
  "name": "Psaki",
  "url": "https:\/\/en.wiktionary.org\/w\/api.php",
  "category_type": "surnames",
  "status": "WikiRecordStatus.page",
  "language_id": "ell",
  "language_script": "Latin",
  "gender": "Gender.unisex",
  "parent_cmtitle": "Category:English surnames from Greek"
 },
 {
  "title": "Rallis",
  "name": "Rallis",
  "url": "https:\/\/en.wiktionary.org\/w\/api.php",
  "category_type": "surnames",
  "status": "WikiRecordStatus.page",
  "language_id": "ell",
  "language_script": "Latin",
  "gender": "Gender.unisex",
  "parent_cmtitle": "Category:English surnames from Greek"
 },
 {
  "title": "Raptis",
  "name": "Raptis",
  "url": "https:\/\/en.wiktionary.org\/w\/api.php",
  "category_type": "surnames",
  "status": "WikiRecordStatus.page",
  "language_id": "ell",
  "language_script": "Latin",
  "gender": "Gender.unisex",
  "parent_cmtitle": "Category:English surnames from Greek"
 },
 {
  "title": "Regas",
  "name": "Regas",
  "url": "https:\/\/en.wiktionary.org\/w\/api.php",
  "category_type": "surnames",
  "status": "WikiRecordStatus.page",
  "language_id": "ell",
  "language_script": "Latin",
  "gender": "Gender.unisex",
  "parent_cmtitle": "Category:English surnames from Greek"
 },
 {
  "title": "Riga",
  "name": "Riga",
  "url": "https:\/\/en.wiktionary.org\/w\/api.php",
  "category_type": "surnames",
  "status": "WikiRecordStatus.page",
  "language_id": "ell",
  "language_script": "Latin",
  "gender": "Gender.unisex",
  "parent_cmtitle": "Category:English surnames from Greek"
 },
 {
  "title": "Romas",
  "name": "Romas",
  "url": "https:\/\/en.wiktionary.org\/w\/api.php",
  "category_type": "surnames",
  "status": "WikiRecordStatus.page",
  "language_id": "ell",
  "language_script": "Latin",
  "gender": "Gender.unisex",
  "parent_cmtitle": "Category:English surnames from Greek"
 },
 {
  "title": "Savas",
  "name": "Savas",
  "url": "https:\/\/en.wiktionary.org\/w\/api.php",
  "category_type": "surnames",
  "status": "WikiRecordStatus.page",
  "language_id": "ell",
  "language_script": "Latin",
  "gender": "Gender.unisex",
  "parent_cmtitle": "Category:English surnames from Greek"
 },
 {
  "title": "Sideris",
  "name": "Sideris",
  "url": "https:\/\/en.wiktionary.org\/w\/api.php",
  "category_type": "surnames",
  "status": "WikiRecordStatus.page",
  "language_id": "ell",
  "language_script": "Latin",
  "gender": "Gender.unisex",
  "parent_cmtitle": "Category:English surnames from Greek"
 },
 {
  "title": "Soter",
  "name": "Soter",
  "url": "https:\/\/en.wiktionary.org\/w\/api.php",
  "category_type": "surnames",
  "status": "WikiRecordStatus.page",
  "language_id": "ell",
  "language_script": "Latin",
  "gender": "Gender.unisex",
  "parent_cmtitle": "Category:English surnames from Greek"
 },
 {
  "title": "Stamoulis",
  "name": "Stamoulis",
  "url": "https:\/\/en.wiktionary.org\/w\/api.php",
  "category_type": "surnames",
  "status": "WikiRecordStatus.page",
  "language_id": "ell",
  "language_script": "Latin",
  "gender": "Gender.unisex",
  "parent_cmtitle": "Category:English surnames from Greek"
 },
 {
  "title": "Stanis",
  "name": "Stanis",
  "url": "https:\/\/en.wiktionary.org\/w\/api.php",
  "category_type": "surnames",
  "status": "WikiRecordStatus.page",
  "language_id": "ell",
  "language_script": "Latin",
  "gender": "Gender.unisex",
  "parent_cmtitle": "Category:English surnames from Greek"
 },
 {
  "title": "Stathis",
  "name": "Stathis",
  "url": "https:\/\/en.wiktionary.org\/w\/api.php",
  "category_type": "surnames",
  "status": "WikiRecordStatus.page",
  "language_id": "ell",
  "language_script": "Latin",
  "gender": "Gender.unisex",
  "parent_cmtitle": "Category:English surnames from Greek"
 },
 {
  "title": "Stathopoulos",
  "name": "Stathopoulos",
  "url": "https:\/\/en.wiktionary.org\/w\/api.php",
  "category_type": "surnames",
  "status": "WikiRecordStatus.page",
  "language_id": "ell",
  "language_script": "Latin",
  "gender": "Gender.unisex",
  "parent_cmtitle": "Category:English surnames from Greek"
 },
 {
  "title": "Stavridis",
  "name": "Stavridis",
  "url": "https:\/\/en.wiktionary.org\/w\/api.php",
  "category_type": "surnames",
  "status": "WikiRecordStatus.page",
  "language_id": "ell",
  "language_script": "Latin",
  "gender": "Gender.unisex",
  "parent_cmtitle": "Category:English surnames from Greek"
 },
 {
  "title": "Stavropoulos",
  "name": "Stavropoulos",
  "url": "https:\/\/en.wiktionary.org\/w\/api.php",
  "category_type": "surnames",
  "status": "WikiRecordStatus.page",
  "language_id": "ell",
  "language_script": "Latin",
  "gender": "Gender.unisex",
  "parent_cmtitle": "Category:English surnames from Greek"
 },
 {
  "title": "Tampakis",
  "name": "Tampakis",
  "url": "https:\/\/en.wiktionary.org\/w\/api.php",
  "category_type": "surnames",
  "status": "WikiRecordStatus.page",
  "language_id": "ell",
  "language_script": "Latin",
  "gender": "Gender.unisex",
  "parent_cmtitle": "Category:English surnames from Greek"
 },
 {
  "title": "Theodorou",
  "name": "Theodorou",
  "url": "https:\/\/en.wiktionary.org\/w\/api.php",
  "category_type": "surnames",
  "status": "WikiRecordStatus.page",
  "language_id": "ell",
  "language_script": "Latin",
  "gender": "Gender.unisex",
  "parent_cmtitle": "Category:English surnames from Greek"
 },
 {
  "title": "Tsitouris",
  "name": "Tsitouris",
  "url": "https:\/\/en.wiktionary.org\/w\/api.php",
  "category_type": "surnames",
  "status": "WikiRecordStatus.page",
  "language_id": "ell",
  "language_script": "Latin",
  "gender": "Gender.unisex",
  "parent_cmtitle": "Category:English surnames from Greek"
 },
 {
  "title": "Tzougros",
  "name": "Tzougros",
  "url": "https:\/\/en.wiktionary.org\/w\/api.php",
  "category_type": "surnames",
  "status": "WikiRecordStatus.page",
  "language_id": "ell",
  "language_script": "Latin",
  "gender": "Gender.unisex",
  "parent_cmtitle": "Category:English surnames from Greek"
 },
 {
  "title": "Varellas",
  "name": "Varellas",
  "url": "https:\/\/en.wiktionary.org\/w\/api.php",
  "category_type": "surnames",
  "status": "WikiRecordStatus.page",
  "language_id": "ell",
  "language_script": "Latin",
  "gender": "Gender.unisex",
  "parent_cmtitle": "Category:English surnames from Greek"
 },
 {
  "title": "Vlachos",
  "name": "Vlachos",
  "url": "https:\/\/en.wiktionary.org\/w\/api.php",
  "category_type": "surnames",
  "status": "WikiRecordStatus.page",
  "language_id": "ell",
  "language_script": "Latin",
  "gender": "Gender.unisex",
  "parent_cmtitle": "Category:English surnames from Greek"
 },
 {
  "title": "Xenakis",
  "name": "Xenakis",
  "url": "https:\/\/en.wiktionary.org\/w\/api.php",
  "category_type": "surnames",
  "status": "WikiRecordStatus.page",
  "language_id": "ell",
  "language_script": "Latin",
  "gender": "Gender.unisex",
  "parent_cmtitle": "Category:English surnames from Greek"
 },
 {
  "title": "Xenides",
  "name": "Xenides",
  "url": "https:\/\/en.wiktionary.org\/w\/api.php",
  "category_type": "surnames",
  "status": "WikiRecordStatus.page",
  "language_id": "ell",
  "language_script": "Latin",
  "gender": "Gender.unisex",
  "parent_cmtitle": "Category:English surnames from Greek"
 },
 {
  "title": "Yiannopoulos",
  "name": "Yiannopoulos",
  "url": "https:\/\/en.wiktionary.org\/w\/api.php",
  "category_type": "surnames",
  "status": "WikiRecordStatus.page",
  "language_id": "ell",
  "language_script": "Latin",
  "gender": "Gender.unisex",
  "parent_cmtitle": "Category:English surnames from Greek"
 },
 {
  "title": "Zervas",
  "name": "Zervas",
  "url": "https:\/\/en.wiktionary.org\/w\/api.php",
  "category_type": "surnames",
  "status": "WikiRecordStatus.page",
  "language_id": "ell",
  "language_script": "Latin",
  "gender": "Gender.unisex",
  "parent_cmtitle": "Category:English surnames from Greek"
 }
]